uddr_client/__init__.py
uddr_client/client.py
uddr_client/connection.py
uddr_client/response.py
uddr_client/api/__init__.py
uddr_client/api/account.py
uddr_client/api/api_client.py
uddr_client/api/decision.py
uddr_client/doh/__init__.py
uddr_client/doh/doh_client.py
uddr_client/doh/ioc_parser.py
uddr_client-0.3.dist-info/LICENSE.md
uddr_client-0.3.dist-info/METADATA
uddr_client-0.3.dist-info/WHEEL
uddr_client-0.3.dist-info/top_level.txt
uddr_client-0.3.dist-info/RECORD
