Metadata-Version: 2.1
Name: uddr-client
Version: 0.3
Summary: A Python client for the UDDR API.
Home-page: https://github.com/sbarbett/uddr_client
Author: Shane Barbetta
Author-email: shane@barbetta.me
License: MIT
Classifier: Development Status :: 3 - Alpha
Classifier: Intended Audience :: Developers
Classifier: License :: OSI Approved :: MIT License
Classifier: Programming Language :: Python :: 3.7
Classifier: Programming Language :: Python :: 3.8
Classifier: Programming Language :: Python :: 3.9
Requires-Python: >=3.7
License-File: LICENSE.md
Requires-Dist: pandas >=2.0.2
Requires-Dist: xmltodict >=0.13.0
Requires-Dist: python-decouple >=3.8
Requires-Dist: requests >=2.25.1
